datasette_vega_dashboards/__init__.py
datasette_vega_dashboards/static/inject.js
datasette_vega_dashboards/static/vega-embed@6
datasette_vega_dashboards/static/vega-lite@5
datasette_vega_dashboards/static/vega@5
datasette_vega_dashboards-1.2.dist-info/LICENSE
datasette_vega_dashboards-1.2.dist-info/METADATA
datasette_vega_dashboards-1.2.dist-info/WHEEL
datasette_vega_dashboards-1.2.dist-info/entry_points.txt
datasette_vega_dashboards-1.2.dist-info/top_level.txt
datasette_vega_dashboards-1.2.dist-info/RECORD
