Metadata-Version: 2.1
Name: datasette-vega-dashboards
Version: 1.2
Summary: Build custom Vega/Vega-Lite dashboards in Datasette.
Home-page: https://github.com/kvakil/datasette-vega-dashboards
Author: Keyhan Vakil
Author-email: kvakil@pypa.kvakil.me
License: Apache License, Version 2.0
Platform: UNKNOWN
Classifier: Framework :: Datasette
Classifier: License :: OSI Approved :: Apache Software License
Requires-Python: >=3.7
License-File: LICENSE
Requires-Dist: datasette
Provides-Extra: test
Requires-Dist: pytest ; extra == 'test'
Requires-Dist: pytest-asyncio ; extra == 'test'
Requires-Dist: httpx ; extra == 'test'
Requires-Dist: sqlite-utils ; extra == 'test'
